biotrainer/__init__.py
biotrainer/autoeval/__init__.py
biotrainer/autoeval/autoeval.py
biotrainer/autoeval/autoeval_progress.py
biotrainer/autoeval/config_bank.py
biotrainer/autoeval/data_handler.py
biotrainer/autoeval/report_manager.py
biotrainer/autoeval/flip/__init__.py
biotrainer/autoeval/flip/flip_config_bank.py
biotrainer/autoeval/flip/flip_conversion_script.py
biotrainer/autoeval/flip/flip_data_handler.py
biotrainer/autoeval/flip/flip_datasets.py
biotrainer/autoeval/pbc/__init__.py
biotrainer/autoeval/pbc/pbc_config_bank.py
biotrainer/autoeval/pbc/pbc_data_handler.py
biotrainer/autoeval/pbc/pbc_datasets.py
biotrainer/config/__init__.py
biotrainer/config/config_exception.py
biotrainer/config/config_option.py
biotrainer/config/config_utils.py
biotrainer/config/config_validation.py
biotrainer/config/configurator.py
biotrainer/config/cross_validation_config.py
biotrainer/config/deprecated_config.py
biotrainer/config/embedding_config.py
biotrainer/config/finetuning_config.py
biotrainer/config/general_config.py
biotrainer/config/hf_dataset_config.py
biotrainer/config/input_config.py
biotrainer/config/model_config.py
biotrainer/config/training_config.py
biotrainer/datasets/__init__.py
biotrainer/datasets/collate_functions.py
biotrainer/datasets/embeddings_dataset.py
biotrainer/embedders/__init__.py
biotrainer/embedders/huggingface/ESM2.py
biotrainer/embedders/huggingface/ProstT5.py
biotrainer/embedders/huggingface/ProtT5.py
biotrainer/embedders/huggingface/__init__.py
biotrainer/embedders/huggingface/huggingface_transformer_embedder.py
biotrainer/embedders/interfaces/__init__.py
biotrainer/embedders/interfaces/bioopt_embedder.py
biotrainer/embedders/interfaces/custom_tokenizer.py
biotrainer/embedders/interfaces/embedder_interfaces.py
biotrainer/embedders/interfaces/preprocessing_strategies.py
biotrainer/embedders/onnx/__init__.py
biotrainer/embedders/onnx/onnx_embedder.py
biotrainer/embedders/predefined_embedders/__init__.py
biotrainer-1.3.0.dist-info/METADATA
biotrainer-1.3.0.dist-info/WHEEL
biotrainer-1.3.0.dist-info/entry_points.txt
biotrainer-1.3.0.dist-info/licenses/LICENSE
biotrainer-1.3.0.dist-info/RECORD
