Metadata-Version: 2.4
Name: biotrainer
Version: 1.3.0
Summary: Biological prediction models made simple.
Project-URL: Issues, https://github.com/sacdallago/biotrainer/issues
Project-URL: Repository, https://github.com/sacdallago/biotrainer
Author-email: Sebastian Franz <sebastian.franz@tum.de>, Christian Dallago <christian.dallago@tum.de>, Joaquin Gomez Sanchez <joaquin.gomez@tum.de>, Michael Heinzinger <mheinzinger@rostlab.org>
License: AFL v3.0
License-File: LICENSE
Classifier: Intended Audience :: Science/Research
Classifier: License :: OSI Approved :: Academic Free License (AFL)
Classifier: Operating System :: OS Independent
Classifier: Programming Language :: Python :: 3
Classifier: Programming Language :: Python :: 3.11
Classifier: Programming Language :: Python :: 3.12
Classifier: Programming Language :: Python :: 3.13
Classifier: Topic :: Scientific/Engineering :: Bio-Informatics
Classifier: Topic :: Scientific/Engineering :: Visualization
Requires-Python: <3.14,>=3.11
Requires-Dist: aaanalysis>=1.0.2
Requires-Dist: accelerate>=1.12.0
Requires-Dist: appdirs>=1.4.4
Requires-Dist: blosum>=2.0.3
Requires-Dist: cyclopts>=3.16.0
Requires-Dist: datasets>=3.5.1
Requires-Dist: h5py<4.0.0,>=3.8.0
Requires-Dist: llvmlite>=0.44.0
Requires-Dist: numpy>=2.1.3
Requires-Dist: onnx==1.19.1
Requires-Dist: onnxscript>=0.5.4
Requires-Dist: peft>=0.15.2
Requires-Dist: protobuf>=5.29.1
Requires-Dist: pydantic>=2.12.3
Requires-Dist: ruamel-yaml<0.18.0,>=0.17.40
Requires-Dist: safetensors>=0.4.4
Requires-Dist: scikit-learn>=1.5.1
Requires-Dist: scipy>=1.15.2
Requires-Dist: sentencepiece>=0.2.0
Requires-Dist: tensorboard>=2.18.0
Requires-Dist: torch<3.0.0,>=2.7.0
Requires-Dist: torchmetrics>=1.7.1
Requires-Dist: tqdm>=4.67.0
Requires-Dist: transformers>=4.57.3
Requires-Dist: umap-learn>=0.5.7
Provides-Extra: dev
Requires-Dist: build>=1.2.2; extra == 'dev'
Requires-Dist: pip-audit>=2.9.0; extra == 'dev'
Requires-Dist: pytest>=8.4.2; extra == 'dev'
Provides-Extra: jupyter
Requires-Dist: jupyter>=1.1.1; extra == 'jupyter'
Requires-Dist: notebook>=7.4.0; extra == 'jupyter'
Provides-Extra: onnx-cpu
Requires-Dist: onnxruntime>=1.23.2; extra == 'onnx-cpu'
Provides-Extra: onnx-gpu
Requires-Dist: onnxruntime-gpu>=1.23.2; extra == 'onnx-gpu'
Provides-Extra: onnx-mac
Requires-Dist: onnxruntime>=1.21.0; extra == 'onnx-mac'
